{
  "timestamp": "2025-08-29T21:39:35.910182",
  "ticker": "PG",
  "data_points": 4995,
  "latest_signal": {
    "date": "2025-08-29",
    "signal": "SELL",
    "position": "FLAT",
    "phase_quadrant": "Quadrante 3 (Picco -> Discesa)",
    "phase_value": 0.031424849527133314,
    "oscillator_value": 1.8612050000000409,
    "signal_strength": 13.430663619285713,
    "confidence": "LOW",
    "price": 157.04,
    "timestamp": "2025-08-29T21:39:33.362407"
  },
  "backtest_metrics": {
    "total_return_%": 162.3151274299507,
    "max_drawdown_%": 0.3829846897438944,
    "sharpe_ratio": 1.4181033452664964,
    "sortino_ratio": Infinity,
    "calmar_ratio": 44.06217469602976,
    "total_trades": 23,
    "win_rate_%": 95.65217391304348,
    "profit_factor": 207.45314823991995
  },
  "cycle_analysis": {
    "dominant_period": 84.0,
    "p_value": 0.0,
    "significant": "True"
  }
}